allure_pg_client/__init__.py
allure_pg_client/db_client.py
allure_pg_client-1.1.2.dist-info/LICENSE
allure_pg_client-1.1.2.dist-info/METADATA
allure_pg_client-1.1.2.dist-info/WHEEL
allure_pg_client-1.1.2.dist-info/RECORD
