Metadata-Version: 2.1
Name: allure-pg-client
Version: 1.1.2
Summary: DBClient that includes allure decorator that logging your queries and query results
Author: amaym0n
Author-email: loco.skitls@gmail.com
Requires-Python: >=3.11,<4.0
Classifier: Programming Language :: Python :: 3
Classifier: Programming Language :: Python :: 3.11
Classifier: Programming Language :: Python :: 3.12
Requires-Dist: allure-pytest (>=2.13.2,<3.0.0)
Requires-Dist: psycopg[binary] (>=3.1.16,<4.0.0)
